<locations>
	<location toloc = "0">
		<name>Бар</name>
		<discr>Вы находитесь в баре, который находится над лабараторией, в которой вам посчастливилось проснуться. Отсюда вы впервый раз смогли увидеть этот новый город. Что же ждет вас дальше? </discr>
	</location>
	<location toloc = "1">
		<name>Порт</name>
		<discr>Главный порт на этом маленьком, но гордом острове, именно через него совершаются все крупные сделки этой страны. Кто правит портом, правит и страной.</discr>
	</location>
</locations>